mcp_quality_pypi/__init__.py
mcp_quality_pypi-0.1.4.dist-info/WHEEL
mcp_quality_pypi-0.1.4.dist-info/entry_points.txt
mcp_quality_pypi-0.1.4.dist-info/METADATA
mcp_quality_pypi-0.1.4.dist-info/RECORD
