Metadata-Version: 2.3
Name: mcp-quality-pypi
Version: 0.1.4
Summary: Add your description here
Author: yanggy
Author-email: yanggy <863007116@qq.com>
Requires-Dist: mcp[cli]>=1.16.0
Requires-Python: >=3.12
